colourlib.py
colourlib-0.4.3.dist-info/LICENSE
colourlib-0.4.3.dist-info/METADATA
colourlib-0.4.3.dist-info/WHEEL
colourlib-0.4.3.dist-info/top_level.txt
colourlib-0.4.3.dist-info/RECORD
