Metadata-Version: 2.1
Name: colourlib
Version: 0.4.3
Summary: Python terminal colour library
Home-page: UNKNOWN
Author: arsikurin
License: UNKNOWN
Platform: UNKNOWN
Requires-Python: >=3.6
